azure_storage2
