Metadata-Version: 1.1
Name: django-azure-storage2
Version: 0.0.4
Summary: Django storage backends for Windows Azure blob storage.
Home-page: https://github.com/Rediker-Software/django-azure-storage
Author: Kevin Brown
Author-email: kbrown@rediker.com
License: MIT
Platform: UNKNOWN
Classifier: Environment :: Web Environment
Classifier: Framework :: Django
Classifier: Intended Audience :: Developers
Classifier: License :: OSI Approved :: MIT License
Classifier: Programming Language :: Python
Classifier: Programming Language :: Python :: 2.6
Classifier: Programming Language :: Python :: 2.7
Classifier: Programming Language :: Python :: 3
Classifier: Programming Language :: Python :: 3.2
Classifier: Programming Language :: Python :: 3.3
Classifier: Programming Language :: Python :: 3.4
